<?xml version="1.0" encoding="UTF-8" standalone="no" ?>
<room xmlns:xsi="http://www.w3.org/2001/XMLSchema-instance">

  <name>penitentiary/penitentiary22.xml</name>

  <scenery>penitentiary</scenery>

  <xTiles>9</xTiles>

  <yTiles>9</yTiles>

  <width>16</width>

  <floorType>none</floorType>

  <floor>
    <tile>
      <x>0</x>
      <y>1</y>
      <offsetX>0</offsetX>
      <offsetY>0</offsetY>
      <bitmap>penitentiary.png/penitentiary-floor-underground-north.png</bitmap>
    </tile>
    <tile>
      <x>0</x>
      <y>2</y>
      <offsetX>0</offsetX>
      <offsetY>0</offsetY>
      <bitmap>penitentiary.png/penitentiary-floor-underground-north.png</bitmap>
    </tile>
    <tile>
      <x>0</x>
      <y>3</y>
      <offsetX>0</offsetX>
      <offsetY>0</offsetY>
      <bitmap>penitentiary.png/penitentiary-floor-underground-north.png</bitmap>
    </tile>
    <tile>
      <x>0</x>
      <y>4</y>
      <offsetX>0</offsetX>
      <offsetY>0</offsetY>
      <bitmap>penitentiary.png/penitentiary-floor-underground-north.png</bitmap>
    </tile>
    <tile>
      <x>0</x>
      <y>5</y>
      <offsetX>0</offsetX>
      <offsetY>0</offsetY>
      <bitmap>penitentiary.png/penitentiary-floor-underground-north.png</bitmap>
    </tile>
    <tile>
      <x>0</x>
      <y>6</y>
      <offsetX>0</offsetX>
      <offsetY>0</offsetY>
      <bitmap>penitentiary.png/penitentiary-floor-underground-north.png</bitmap>
    </tile>
    <tile>
      <x>0</x>
      <y>7</y>
      <offsetX>0</offsetX>
      <offsetY>0</offsetY>
      <bitmap>penitentiary.png/penitentiary-floor-underground-north.png</bitmap>
    </tile>
    <tile>
      <x>0</x>
      <y>8</y>
      <offsetX>0</offsetX>
      <offsetY>0</offsetY>
      <bitmap>penitentiary.png/penitentiary-floor-underground-north.png</bitmap>
    </tile>
    <tile>
      <x>1</x>
      <y>0</y>
      <offsetX>0</offsetX>
      <offsetY>0</offsetY>
      <bitmap>penitentiary.png/penitentiary-floor-underground-east.png</bitmap>
    </tile>
    <tile>
      <x>2</x>
      <y>0</y>
      <offsetX>0</offsetX>
      <offsetY>0</offsetY>
      <bitmap>penitentiary.png/penitentiary-floor-underground-east.png</bitmap>
    </tile>
    <tile>
      <x>3</x>
      <y>0</y>
      <offsetX>0</offsetX>
      <offsetY>0</offsetY>
      <bitmap>penitentiary.png/penitentiary-floor-underground-east.png</bitmap>
    </tile>
    <tile>
      <x>4</x>
      <y>0</y>
      <offsetX>0</offsetX>
      <offsetY>0</offsetY>
      <bitmap>penitentiary.png/penitentiary-floor-underground-east.png</bitmap>
    </tile>
    <tile>
      <x>5</x>
      <y>0</y>
      <offsetX>0</offsetX>
      <offsetY>0</offsetY>
      <bitmap>penitentiary.png/penitentiary-floor-underground-east.png</bitmap>
    </tile>
    <tile>
      <x>6</x>
      <y>0</y>
      <offsetX>0</offsetX>
      <offsetY>0</offsetY>
      <bitmap>penitentiary.png/penitentiary-floor-underground-east.png</bitmap>
    </tile>
    <tile>
      <x>7</x>
      <y>0</y>
      <offsetX>0</offsetX>
      <offsetY>0</offsetY>
      <bitmap>penitentiary.png/penitentiary-floor-underground-east.png</bitmap>
    </tile>
    <tile>
      <x>8</x>
      <y>0</y>
      <offsetX>0</offsetX>
      <offsetY>0</offsetY>
      <bitmap>penitentiary.png/penitentiary-floor-underground-east.png</bitmap>
    </tile>
    <tile>
      <x>8</x>
      <y>1</y>
      <offsetX>0</offsetX>
      <offsetY>0</offsetY>
      <bitmap>penitentiary.png/penitentiary-nofloor-south.png</bitmap>
    </tile>
    <tile>
      <x>8</x>
      <y>2</y>
      <offsetX>0</offsetX>
      <offsetY>0</offsetY>
      <bitmap>penitentiary.png/penitentiary-nofloor-south.png</bitmap>
    </tile>
    <tile>
      <x>8</x>
      <y>3</y>
      <offsetX>0</offsetX>
      <offsetY>0</offsetY>
      <bitmap>penitentiary.png/penitentiary-nofloor-south.png</bitmap>
    </tile>
    <tile>
      <x>8</x>
      <y>4</y>
      <offsetX>0</offsetX>
      <offsetY>0</offsetY>
      <bitmap>penitentiary.png/penitentiary-nofloor-south.png</bitmap>
    </tile>
    <tile>
      <x>8</x>
      <y>5</y>
      <offsetX>0</offsetX>
      <offsetY>0</offsetY>
      <bitmap>penitentiary.png/penitentiary-nofloor-south.png</bitmap>
    </tile>
    <tile>
      <x>8</x>
      <y>6</y>
      <offsetX>0</offsetX>
      <offsetY>0</offsetY>
      <bitmap>penitentiary.png/penitentiary-nofloor-south.png</bitmap>
    </tile>
    <tile>
      <x>8</x>
      <y>7</y>
      <offsetX>0</offsetX>
      <offsetY>0</offsetY>
      <bitmap>penitentiary.png/penitentiary-nofloor-south.png</bitmap>
    </tile>
    <tile>
      <x>1</x>
      <y>8</y>
      <offsetX>0</offsetX>
      <offsetY>0</offsetY>
      <bitmap>penitentiary.png/penitentiary-nofloor-west.png</bitmap>
    </tile>
    <tile>
      <x>2</x>
      <y>8</y>
      <offsetX>0</offsetX>
      <offsetY>0</offsetY>
      <bitmap>penitentiary.png/penitentiary-nofloor-west.png</bitmap>
    </tile>
    <tile>
      <x>3</x>
      <y>8</y>
      <offsetX>0</offsetX>
      <offsetY>0</offsetY>
      <bitmap>penitentiary.png/penitentiary-nofloor-west.png</bitmap>
    </tile>
    <tile>
      <x>4</x>
      <y>8</y>
      <offsetX>0</offsetX>
      <offsetY>0</offsetY>
      <bitmap>penitentiary.png/penitentiary-nofloor-west.png</bitmap>
    </tile>
    <tile>
      <x>5</x>
      <y>8</y>
      <offsetX>0</offsetX>
      <offsetY>0</offsetY>
      <bitmap>penitentiary.png/penitentiary-nofloor-west.png</bitmap>
    </tile>
    <tile>
      <x>6</x>
      <y>8</y>
      <offsetX>0</offsetX>
      <offsetY>0</offsetY>
      <bitmap>penitentiary.png/penitentiary-nofloor-west.png</bitmap>
    </tile>
    <tile>
      <x>7</x>
      <y>8</y>
      <offsetX>0</offsetX>
      <offsetY>0</offsetY>
      <bitmap>penitentiary.png/penitentiary-nofloor-west.png</bitmap>
    </tile>
    <tile>
      <x>8</x>
      <y>8</y>
      <offsetX>0</offsetX>
      <offsetY>0</offsetY>
      <bitmap>penitentiary.png/penitentiary-nofloor-sw.png</bitmap>
    </tile>
  </floor>

  <items>
    <item x="0" y="1" z="0">
      <label>penitentiary-wall-x-2</label>
      <direction>none</direction>
      <type>griditem</type>
    </item>
    <item x="0" y="2" z="0">
      <label>penitentiary-wall-x-2</label>
      <direction>none</direction>
      <type>griditem</type>
    </item>
    <item x="0" y="3" z="0">
      <label>penitentiary-wall-y-2</label>
      <direction>none</direction>
      <type>griditem</type>
    </item>
    <item x="0" y="4" z="0">
      <label>penitentiary-wall-x-2</label>
      <direction>none</direction>
      <type>griditem</type>
    </item>
    <item x="0" y="5" z="0">
      <label>penitentiary-wall-x-2</label>
      <direction>none</direction>
      <type>griditem</type>
    </item>
    <item x="0" y="6" z="0">
      <label>penitentiary-wall-y-2</label>
      <direction>none</direction>
      <type>griditem</type>
    </item>
    <item x="0" y="7" z="0">
      <label>penitentiary-wall-x-2</label>
      <direction>none</direction>
      <type>griditem</type>
    </item>
    <item x="0" y="8" z="0">
      <label>penitentiary-wall-x-2</label>
      <direction>none</direction>
      <type>griditem</type>
    </item>
    <item x="1" y="0" z="0">
      <label>penitentiary-wall-x-1</label>
      <direction>none</direction>
      <type>griditem</type>
    </item>
    <item x="2" y="0" z="0">
      <label>penitentiary-wall-x-1</label>
      <direction>none</direction>
      <type>griditem</type>
    </item>
    <item x="3" y="0" z="0">
      <label>penitentiary-wall-x-2</label>
      <direction>none</direction>
      <type>griditem</type>
    </item>
    <item x="4" y="0" z="0">
      <label>penitentiary-wall-x-1</label>
      <direction>none</direction>
      <type>griditem</type>
    </item>
    <item x="5" y="0" z="0">
      <label>penitentiary-wall-x-1</label>
      <direction>none</direction>
      <type>griditem</type>
    </item>
    <item x="6" y="0" z="0">
      <label>penitentiary-wall-x-2</label>
      <direction>none</direction>
      <type>griditem</type>
    </item>
    <item x="7" y="0" z="0">
      <label>penitentiary-wall-x-1</label>
      <direction>none</direction>
      <type>griditem</type>
    </item>
    <item x="8" y="0" z="0">
      <label>penitentiary-wall-x-1</label>
      <direction>none</direction>
      <type>griditem</type>
    </item>
    <item x="1" y="1" z="0">
      <label>brick2</label>
      <direction>none</direction>
      <type>griditem</type>
    </item>
    <item x="2" y="1" z="0">
      <label>brick2</label>
      <direction>none</direction>
      <type>griditem</type>
    </item>
    <item x="3" y="1" z="0">
      <label>brick2</label>
      <direction>none</direction>
      <type>griditem</type>
    </item>
    <item x="4" y="1" z="0">
      <label>brick2</label>
      <direction>none</direction>
      <type>griditem</type>
    </item>
    <item x="5" y="1" z="0">
      <label>brick2</label>
      <direction>none</direction>
      <type>griditem</type>
    </item>
    <item x="6" y="1" z="0">
      <label>brick2</label>
      <direction>none</direction>
      <type>griditem</type>
    </item>
    <item x="7" y="1" z="0">
      <label>brick2</label>
      <direction>none</direction>
      <type>griditem</type>
    </item>
    <item x="8" y="1" z="0">
      <label>brick2</label>
      <direction>none</direction>
      <type>griditem</type>
    </item>
    <item x="1" y="2" z="0">
      <label>brick2</label>
      <direction>none</direction>
      <type>griditem</type>
    </item>
    <item x="8" y="2" z="0">
      <label>brick2</label>
      <direction>none</direction>
      <type>griditem</type>
    </item>
    <item x="1" y="3" z="0">
      <label>brick2</label>
      <direction>none</direction>
      <type>griditem</type>
    </item>
    <item x="8" y="3" z="0">
      <label>brick2</label>
      <direction>none</direction>
      <type>griditem</type>
    </item>
    <item x="1" y="4" z="0">
      <label>brick2</label>
      <direction>none</direction>
      <type>griditem</type>
    </item>
    <item x="4" y="4" z="4">
      <label>brick1</label>
      <direction>none</direction>
      <type>griditem</type>
    </item>
    <item x="4" y="4" z="5">
      <label>extra-life</label>
      <direction>west</direction>
      <behavior>behavior of something special</behavior>
      <type>freeitem</type>
    </item>
    <item x="5" y="4" z="4">
      <label>brick1</label>
      <direction>none</direction>
      <type>griditem</type>
    </item>
    <item x="6" y="4" z="5">
      <label>brick2</label>
      <direction>none</direction>
      <behavior>behavior of disappearance on jump into</behavior>
      <type>griditem</type>
    </item>
    <item x="7" y="4" z="6">
      <label>brick2</label>
      <direction>none</direction>
      <behavior>behavior of disappearance on jump into</behavior>
      <type>griditem</type>
    </item>
    <item x="8" y="4" z="0">
      <label>brick2</label>
      <direction>none</direction>
      <type>griditem</type>
    </item>
    <item x="8" y="4" z="7">
      <label>brick1</label>
      <direction>none</direction>
      <type>griditem</type>
    </item>
    <item x="1" y="5" z="0">
      <label>brick2</label>
      <direction>none</direction>
      <type>griditem</type>
    </item>
    <item x="4" y="5" z="3">
      <label>brick2</label>
      <direction>none</direction>
      <behavior>behavior of disappearance on jump into</behavior>
      <type>griditem</type>
    </item>
    <item x="8" y="5" z="0">
      <label>brick2</label>
      <direction>none</direction>
      <type>griditem</type>
    </item>
    <item x="1" y="6" z="0">
      <label>brick2</label>
      <direction>none</direction>
      <type>griditem</type>
    </item>
    <item x="4" y="6" z="2">
      <label>brick2</label>
      <direction>none</direction>
      <behavior>behavior of disappearance on jump into</behavior>
      <type>griditem</type>
    </item>
    <item x="8" y="6" z="0">
      <label>brick2</label>
      <direction>none</direction>
      <type>griditem</type>
    </item>
    <item x="1" y="7" z="0">
      <label>brick2</label>
      <direction>none</direction>
      <type>griditem</type>
    </item>
    <item x="4" y="7" z="1">
      <label>brick2</label>
      <direction>none</direction>
      <behavior>behavior of disappearance on jump into</behavior>
      <type>griditem</type>
    </item>
    <item x="8" y="7" z="0">
      <label>brick2</label>
      <direction>none</direction>
      <type>griditem</type>
    </item>
    <item x="1" y="8" z="0">
      <label>brick2</label>
      <direction>none</direction>
      <type>griditem</type>
    </item>
    <item x="2" y="8" z="0">
      <label>brick2</label>
      <direction>none</direction>
      <type>griditem</type>
    </item>
    <item x="3" y="8" z="0">
      <label>brick2</label>
      <direction>none</direction>
      <type>griditem</type>
    </item>
    <item x="4" y="8" z="0">
      <label>brick2</label>
      <direction>none</direction>
      <type>griditem</type>
    </item>
    <item x="5" y="8" z="0">
      <label>brick2</label>
      <direction>none</direction>
      <type>griditem</type>
    </item>
    <item x="6" y="8" z="0">
      <label>brick2</label>
      <direction>none</direction>
      <type>griditem</type>
    </item>
    <item x="7" y="8" z="0">
      <label>brick2</label>
      <direction>none</direction>
      <type>griditem</type>
    </item>
    <item x="8" y="8" z="0">
      <label>brick2</label>
      <direction>none</direction>
      <type>griditem</type>
    </item>
  </items>

</room>
